{
    "resourceType": "ValueSet",
    "id": "1.2.276.0.76.11.58--20180713162142",
    "meta": {
        "profile": [
            "http://hl7.org/fhir/StructureDefinition/shareablevalueset"
        ]
    },
    "extension": [
        {
            "url": "http://hl7.org/fhir/StructureDefinition/resource-effectivePeriod",
            "valuePeriod": {
                "start": "2018-07-13T16:21:42+01:00"
            }
        }
    ],
    "url": "http://art-decor.org/fhir/ValueSet/1.2.276.0.76.11.58--20180713162142",
    "identifier": [
        {
            "use": "official",
            "system": "http://art-decor.org/ns/oids/vs",
            "value": "1.2.276.0.76.11.58"
        }
    ],
    "version": "2018-07-13T16:21:42",
    "name": "IHEXDShealthcareFacilityTypeCodePatientReleatedHealthcare",
    "title": "IHE XDS healthcareFacilityTypeCode Patient Related Healthcare",
    "status": "active",
    "experimental": false,
    "publisher": "IHE Deutschland e.V.",
    "description": "**healthcareFacilityTypeCode (XDSDocumentEntry)**\r\n This code for an XDS Document represents the type of organizational setting of the clinical encounter during which the documented act occurred.",
    "immutable": false,
    "compose": {
        "include": [
            {
                "system": "http://ihe-d.de/CodeSystems/PatientBezogenenGesundheitsversorgung",
                "concept": [
                    {
                        "extension": [
                            {
                                "url": "http://hl7.org/fhir/StructureDefinition/valueset-concept-comments",
                                "valueString": "Sozialstationen und gewerblich betriebene ambulante Pflegedienste, die Patienten in der eigenen h\u00e4uslichen Umgebung betreuen, aber keine \u00e4rztlichen T\u00e4tigkeiten durchf\u00fchren."
                            }
                        ],
                        "code": "APD",
                        "display": "Ambulanter Pflegedienst"
                    },
                    {
                        "extension": [
                            {
                                "url": "http://hl7.org/fhir/StructureDefinition/valueset-concept-comments",
                                "valueString": "Eine Einrichtung zur Abgabe und ggf. Lagerung oder Herstellung von Arzneimitteln. Dieser Wert sollte nicht zur Kennzeichnung von Daten aus Krankenhausapotheken verwendet werden."
                            }
                        ],
                        "code": "APO",
                        "display": "Apotheke"
                    },
                    {
                        "extension": [
                            {
                                "url": "http://hl7.org/fhir/StructureDefinition/valueset-concept-comments",
                                "valueString": "Der \u00e4rztliche Bereitschaftsdienst wird auch als Kassen\u00e4rztlicher Notdienst bezeichnet. Er wird h\u00e4ufig durch Niedergelassene \u00c4rzte durchgef\u00fchrt und von der Kassen\u00e4rztlichen Vereinigungen organisiert, da diese die Verantwortung f\u00fcr die Sicherstellung der medizinischen Versorgung auch au\u00dferhalb der \u00fcblichen \u00d6ffnungszeiten hat. Der Dienst ist vom Rettungsdienst zu unterscheiden, der auf speziell ausgebildete Not\u00e4rzte zur\u00fcckgreift."
                            }
                        ],
                        "code": "BER",
                        "display": "\u00c4rztlicher Bereitschaftsdienst"
                    },
                    {
                        "extension": [
                            {
                                "url": "http://hl7.org/fhir/StructureDefinition/valueset-concept-comments",
                                "valueString": "Arbeitsplatz einer oder mehrerer niedergelassenen \u00c4rztinnen oder Zahn\u00e4rztinnen. Umfasst sowohl den klassischen \"Einzelsitz\", wie auch die Gemeinschaftspraxis oder die Praxisgemeinschaft. Auch mobile Arztpraxen, die ambulante Zentrumsdialyse (https://www.gbe-bund.de/glossar/Dialyseversorgungsarten.html) und Zahnarztpraxen werden durch diesen Wert abgedeckt. Ebenso werden niedergelassene Laborarztpraxen und von \u00e4rztlichen Psychotherapeuten gef\u00fchrte Arztpraxen \u00fcber diesen Wert abgedeckt. Arztpraxen die Teil eines MVZ sind werden \u00fcber das Konzept MVZ (\"Medizinisches Versorgungszentrum\") abgebildet."
                            }
                        ],
                        "code": "PRA",
                        "display": "Arztpraxis"
                    },
                    {
                        "extension": [
                            {
                                "url": "http://hl7.org/fhir/StructureDefinition/valueset-concept-comments",
                                "valueString": "Betriebs\u00e4rztliche Abteilung in einer nicht-medizinischen Organisation (z.B. gro\u00dfe Firmen die selbst \u00c4rzte anstellen) die eine medizinische Betreuung f\u00fcr Mitarbeiter anbietet. Betriebs\u00e4rztliche T\u00e4tigkeiten einer \u00c4rztin mit eigener Praxis oder eines Diensts eines Krankenhauses fallen nicht unter dieses Konzept, sondern werden mit dem Konzept PRA (\"Arztpraxis\"), bzw. KHS (\"Krankenhaus\") abgebildet."
                            }
                        ],
                        "code": "BAA",
                        "display": "Betriebs\u00e4rztliche Abteilung"
                    },
                    {
                        "extension": [
                            {
                                "url": "http://hl7.org/fhir/StructureDefinition/valueset-concept-comments",
                                "valueString": "Staatliche oder kommunale Gesundheitsbeh\u00f6rde."
                            }
                        ],
                        "code": "BHR",
                        "display": "Gesundheitsbeh\u00f6rde"
                    },
                    {
                        "extension": [
                            {
                                "url": "http://hl7.org/fhir/StructureDefinition/valueset-concept-comments",
                                "valueString": "Eine freiberuflich t\u00e4tige Hebamme; bzw. eine in Kooperation mit anderen Hebammen t\u00e4tige Hebamme. Dieser Wert deckt auch Geburtsh\u00e4user ab, d.h. \u00fcblicherweise von Hebammen betriebene au\u00dferklinische Einrichtungen."
                            }
                        ],
                        "code": "HEB",
                        "display": "Hebamme/Geburtshaus"
                    },
                    {
                        "extension": [
                            {
                                "url": "http://hl7.org/fhir/StructureDefinition/valueset-concept-comments",
                                "valueString": "Eine station\u00e4re oder ambulante Einrichtung der Sterbebegleitung. Dies umfasst sowohl Pflegeheim-\u00e4hnliche Einrichtungen, wie auch Einrichtungen die den Patienten in der eigenen h\u00e4uslichen Umgebung betreuen. Sowohl Einrichtungen unter \u00e4rztlicher Leitung, wie auch unter pflegerischer Leitung werden hier zusammengefasst."
                            }
                        ],
                        "code": "HOS",
                        "display": "Hospiz"
                    },
                    {
                        "extension": [
                            {
                                "url": "http://hl7.org/fhir/StructureDefinition/valueset-concept-comments",
                                "valueString": "Eine Einrichtung die als Krankenhaus nach dem Krankenhausfinanzierungsgesetz (KHG) zu verstehen ist, mit Ausnahme von Reha-Kliniken. Zu den Krankenh\u00e4usern geh\u00f6ren hierbei auch Zahnkliniken. Zus\u00e4tzlich fallen unter diesen Wert auch Krankenh\u00e4user auf die das KHG keine Anwendung findet (siehe \u00a73, z.B. im Straf- oder Ma\u00dfregelvollzug, Polizeikrankenh\u00e4user, Bundeswehrkrankenh\u00e4user...), solange es sich nicht um Einrichtungen der medizinischen Rehabilitation handelt.  F\u00fcr Dokumente aus der Abteilung Krankenhausapotheke oder aus Krankenhausambulanzen\n          sollte immer das Konzept KHS \"Krankenhaus\" verwendet werden. Auch bei vornehmlich telemedizinisch erbrachten Leistungen eines Krankenhauses (z.B. Teleradiologie) sollte das Konzept KHS \"Krankenhaus\"\" verwendet werden.  F\u00fcr angeschlossene, aber selbst\u00e4ndige Einrichtungen, wie z.B. ein zum Krankenhaus geh\u00f6riges MVZ oder Hospiz, sollte dieses Konzept (KHS \"Krankenhaus\"), sondern ein spezifischeres Konzept f\u00fcr den Einrichtungstyp verwendet werden. Dazu z\u00e4hlen auch ausgegr\u00fcndete Labore, die als Arztpraxis abgebildet werden, da sie eine entsprechende KV-Zulassung ben\u00f6tigen. \n          Psychotherapeutische, psychiatrische und psychosomatische Abteilungen von Krankenh\u00e4usern und eigenst\u00e4ndige Fachkliniken aus diesem Bereich werden auch mit diesem Wert abgedeckt, unabh\u00e4ngig davon ob die Dienste station\u00e4r, als Tagesklinik oder ambulant angeboten werden."
                            }
                        ],
                        "code": "KHS",
                        "display": "Krankenhaus"
                    },
                    {
                        "extension": [
                            {
                                "url": "http://hl7.org/fhir/StructureDefinition/valueset-concept-comments",
                                "valueString": "Einrichtung zur ambulanten medizinischen Versorgung nach \u00a795 SGB V; dieses Konzept sollte f\u00fcr ein MVZ unabh\u00e4ngig von der Besitzerstruktur gew\u00e4hlt werden, d.h. auch MVZ die einem Krankenhaus geh\u00f6ren, sollten als MVZ gekennzeichnet werden."
                            }
                        ],
                        "code": "MVZ",
                        "display": "Medizinisches Versorgungszentrum"
                    },
                    {
                        "extension": [
                            {
                                "url": "http://hl7.org/fhir/StructureDefinition/valueset-concept-comments",
                                "valueString": "Eine Einrichtung des medizinisch-technischen Handwerks, wie Augenoptiker, H\u00f6rakustiker-Fachgesch\u00e4ft, Di\u00e4tkoch, Orthop\u00e4dische Schuhmacher, sowie Orthop\u00e4dische Fachgesch\u00e4fte und Sanit\u00e4tsh\u00e4user."
                            }
                        ],
                        "code": "HAN",
                        "display": "Medizinisch-technisches Handwerk"
                    },
                    {
                        "extension": [
                            {
                                "url": "http://hl7.org/fhir/StructureDefinition/valueset-concept-comments",
                                "valueString": "Eine ambulante, teilstation\u00e4re oder station\u00e4re Einrichtung der medizinischen Rehabilitation unter \u00e4rztlicher Leitung. Darunter fallen sowohl Kur-Einrichtungen und Reha-Kliniken als auch dezentrale Organisationsformen aus dem ambulanten Sektor."
                            }
                        ],
                        "code": "REH",
                        "display": "Medizinische Rehabilitation"
                    },
                    {
                        "extension": [
                            {
                                "url": "http://hl7.org/fhir/StructureDefinition/valueset-concept-comments",
                                "valueString": "Von nicht-\u00e4rztlichen Heilberuflern betriebene Einrichtungen zur Beratung, Therapie oder Betreuung. Darunter fallen Praxen von Heilpraktikerinnen, Physiotherapeutinnen, Ergotherapeutinnen, Podologinnen, Masseurinnen, Logop\u00e4dinnen, Sprachtherapeutinnen, Di\u00e4tassistentinnen, sowie human-medizinische Beratungsstellen. Auch nicht-\u00e4rztliche psychotherapeutische Praxen, z.B. von Diplom oder Master-Psychologen, geh\u00f6ren dazu.  Dokumente von freiberuflichen Hebammen fallen nicht in diese Gruppe, sondern sind mit dem Konzept f\u00fcr HEB \"Hebamme/Geburtshaus\" zu\n          kennzeichnen.  Dokumente von Pflegediensten oder freiberuflichen Pflegekr\u00e4ften fallen nicht in diese Gruppe sondern sind mit dem Konzept APD \u00a0\"Ambulante Pflegedienste\" zu kennzeichnen."
                            }
                        ],
                        "code": "HEI",
                        "display": "Nicht-\u00e4rztliche Heilberufs-Praxis"
                    },
                    {
                        "extension": [
                            {
                                "url": "http://hl7.org/fhir/StructureDefinition/valueset-concept-comments",
                                "valueString": "Eine Einrichtung zur Unterbringung und Versorgung pflegebed\u00fcrftiger Menschen. Umfasst Altenpflegeheime und Pflegeheime f\u00fcr Menschen mit Behinderung. Die Einrichtungen versorgen Menschen \u00fcblicherweise langfristig, aber auch Kurzzeitpflege der genannten Personengruppen ist durch dieses Konzept abgedeckt."
                            }
                        ],
                        "code": "PFL",
                        "display": "Pflegeheim"
                    },
                    {
                        "extension": [
                            {
                                "url": "http://hl7.org/fhir/StructureDefinition/valueset-concept-comments",
                                "valueString": "Einrichtungen des zivilen Rettungsdienst, wie z.B. Rettungswachen, Wasserrettung, etc."
                            }
                        ],
                        "code": "RTN",
                        "display": "Rettungsdienst"
                    },
                    {
                        "extension": [
                            {
                                "url": "http://hl7.org/fhir/StructureDefinition/valueset-concept-comments",
                                "valueString": "Einrichtungen zur Information und Beratung zur Selbsthilfe sowie Selbsthilfegruppen, z.B. Suchtberatung, AIDS-Hilfe, etc."
                            }
                        ],
                        "code": "SEL",
                        "display": "Selbsthilfe"
                    },
                    {
                        "extension": [
                            {
                                "url": "http://hl7.org/fhir/StructureDefinition/valueset-concept-comments",
                                "valueString": "Eine dedizierte Einrichtung die ausschlie\u00dflich auf die telemedizinische Betreuung von Patienten abzielt. Dies umfasst sowohl dedizierte Care Management Organisationen, wie auch Telemonitoring-Zentren. Dokumente die im Rahmen von telemedizinischen Dienstleistungen von Krankenh\u00e4usern oder niedergelassenen \u00c4rzten erbracht werden, sollten nicht mit diesem Konzept gekennzeichnet werden, sondern mit dem Konzept f\u00fcr KHS \"Krankenhaus\" bzw. PRA \"Arztpraxis\"."
                            }
                        ],
                        "code": "TMZ",
                        "display": "Telemedizinisches Zentrum"
                    }
                ]
            }
        ]
    }
}
